py_geodetector/__init__.py
py_geodetector/geodetector.py
py_geodetector/example_data/disease.csv
py_geodetector-0.1.3.dist-info/METADATA
py_geodetector-0.1.3.dist-info/WHEEL
py_geodetector-0.1.3.dist-info/RECORD
