Metadata-Version: 2.3
Name: py_geodetector
Version: 0.1.3
Summary: A simple Python package for the geodetector
Project-URL: Homepage, https://github.com/djw-easy/GeoDetector
Project-URL: Bug Tracker, https://github.com/djw-easy/GeoDetector/issues
Author-email: djw <djweasy@163.com>
Classifier: License :: OSI Approved :: MIT License
Classifier: Operating System :: OS Independent
Classifier: Programming Language :: Python :: 3
Requires-Python: >=3.7
